singleton_base/__init__.py
singleton_base/_common.py
singleton_base/py.typed
singleton_base/singleton_base.py
singleton_base/singleton_meta.py
singleton_base/singleton_wrapper.py
singleton_base-1.2.3.dist-info/METADATA
singleton_base-1.2.3.dist-info/WHEEL
singleton_base-1.2.3.dist-info/RECORD
