Metadata-Version: 2.4
Name: singleton-base
Version: 1.2.3
Summary: A type-friendly, thread-safe singleton base class for Python 3.9+. Very simple to use and test-friendly.
Author-email: chaz <bright.lid5647@fastmail.com>
Requires-Python: >=3.9
Requires-Dist: typing-extensions>=4.15.0
